govaitextextract/__init__.py
govaitextextract/main.py
govaitextextract/prompts.py
govaitextextract-2025.12.21194243.dist-info/METADATA
govaitextextract-2025.12.21194243.dist-info/WHEEL
govaitextextract-2025.12.21194243.dist-info/top_level.txt
govaitextextract-2025.12.21194243.dist-info/RECORD
