Metadata-Version: 2.4
Name: govaitextextract
Version: 2025.12.21194243
Summary: govaitextextract extracts structured AI/tech initiative data from text for policy, news, and recruitment analysis.
Author-email: govaitextextract <hi@eugene.plus>
License: MIT
Project-URL: Homepage, https://github.com/chigwell/govaitextextract
Requires-Python: >=3.9
Requires-Dist: langchain-llm7>=0.0.0
Requires-Dist: llmatch-messages>=0.0.0
Requires-Dist: langchain-core>=0.3.0
